seismicrna/__init__.py
seismicrna/ensembles.py
seismicrna/interface.py
seismicrna/join.py
seismicrna/lists.py
seismicrna/main.py
seismicrna/migrate.py
seismicrna/pool.py
seismicrna/table.py
seismicrna/urls.py
seismicrna/wf.py
seismicrna/align/__init__.py
seismicrna/align/fqunit.py
seismicrna/align/main.py
seismicrna/align/report.py
seismicrna/align/split.py
seismicrna/align/write.py
seismicrna/align/xamops.py
seismicrna/align/tests/__init__.py
seismicrna/align/tests/write_test.py
seismicrna/align/tests/xamgen_test.py
seismicrna/align/tests/xamops_test.py
seismicrna/cleanfa/__init__.py
seismicrna/cleanfa/cleanfa.py
seismicrna/cleanfa/main.py
seismicrna/cluster/__init__.py
seismicrna/cluster/batch.py
seismicrna/cluster/data.py
seismicrna/cluster/em.py
seismicrna/cluster/emk.py
seismicrna/cluster/io.py
seismicrna/cluster/jackpot.py
seismicrna/cluster/main.py
seismicrna/cluster/marginal.py
seismicrna/cluster/names.py
seismicrna/cluster/obsexp.py
seismicrna/cluster/params.py
seismicrna/cluster/report.py
seismicrna/cluster/summary.py
seismicrna/cluster/uniq.py
seismicrna/cluster/write.py
seismicrna/cluster/tests/__init__.py
seismicrna/cluster/tests/emk_test.py
seismicrna/cluster/tests/jackpot_test.py
seismicrna/cluster/tests/marginal_test.py
seismicrna/core/__init__.py
seismicrna/core/array.py
seismicrna/core/dataset.py
seismicrna/core/error.py
seismicrna/core/header.py
seismicrna/core/join.py
seismicrna/core/lists.py
seismicrna/core/logs.py
seismicrna/core/path.py
seismicrna/core/random.py
seismicrna/core/report.py
seismicrna/core/run.py
seismicrna/core/stats.py
seismicrna/core/task.py
seismicrna/core/tmp.py
seismicrna/core/types.py
seismicrna/core/unbias.py
seismicrna/core/validate.py
seismicrna/core/version.py
seismicrna/core/write.py
seismicrna/core/arg/__init__.py
seismicrna/core/arg/cli.py
seismicrna/core/arg/cmd.py
seismicrna/core/arg/default.py
seismicrna/core/arg/docdef.py
seismic_rna-0.24.3.dist-info/METADATA
seismic_rna-0.24.3.dist-info/WHEEL
seismic_rna-0.24.3.dist-info/entry_points.txt
seismic_rna-0.24.3.dist-info/RECORD
