Metadata-Version: 2.1
Name: seismic-rna
Version: 0.24.3
Summary: Structure Ensemble Inference by Sequencing, Mutation Identification, and Clustering of RNA (SEISMIC-RNA)
Author: Matty Allan, Scott Grote, Justin Aruda, Yves Martin, Alberic de Lajarte
License: GPL-3.0-only
Classifier: Programming Language :: Python :: 3
Classifier: Operating System :: OS Independent
Project-URL: Homepage, https://github.com/rouskinlab/seismic-rna
Project-URL: Bug Tracker, https://github.com/rouskinlab/seismic-rna/issues
Requires-Python: >=3.11
Requires-Dist: brotli>=1.0
Requires-Dist: click>=8.1
Requires-Dist: fastqsplitter>=1.2
Requires-Dist: kaleido==0.2.1
Requires-Dist: networkx>=3.4
Requires-Dist: numpy<2.2,>=2.0
Requires-Dist: numba>=0.61
Requires-Dist: pandas>=2.2
Requires-Dist: plotly>=5.23
Requires-Dist: pyyaml>=6.0
Requires-Dist: scipy>=1.13
Requires-Dist: jinja2>=3.0
Requires-Dist: jgo>=1.0
